specify_cli/__init__.py
speckit/__init__.py
speckit/cli.py
speckit/config.py
speckit/exceptions.py
speckit/llm.py
speckit/py.typed
speckit/schemas.py
speckit/speckit.py
speckit/core/__init__.py
speckit/core/analyzer.py
speckit/core/artifacts.py
speckit/core/clarifier.py
speckit/core/constitution.py
speckit/core/implementer.py
speckit/core/planner.py
speckit/core/specification.py
speckit/core/tasker.py
speckit/mcp/__init__.py
speckit/mcp/__main__.py
speckit/mcp/server.py
speckit/storage/__init__.py
speckit/storage/base.py
speckit/storage/file_storage.py
speckit/templates/__init__.py
speckit/templates/analyze.jinja2
speckit/templates/api_contract.jinja2
speckit/templates/checklist.jinja2
speckit/templates/clarify.jinja2
speckit/templates/constitution.jinja2
speckit/templates/data_model.jinja2
speckit/templates/plan.jinja2
speckit/templates/quickstart.jinja2
speckit/templates/research.jinja2
speckit/templates/specification.jinja2
speckit/templates/tasks.jinja2
speckit_ai-0.2.4.dist-info/METADATA
speckit_ai-0.2.4.dist-info/WHEEL
speckit_ai-0.2.4.dist-info/entry_points.txt
speckit_ai-0.2.4.dist-info/licenses/LICENSE
speckit_ai-0.2.4.dist-info/RECORD
