Metadata-Version: 2.4
Name: speckit-ai
Version: 0.2.4
Summary: A Python library for spec-driven development with universal LLM support via LiteLLM.
Project-URL: Homepage, https://github.com/suportly/spec-kit
Project-URL: Documentation, https://github.com/suportly/spec-kit#readme
Project-URL: Repository, https://github.com/suportly/spec-kit
Project-URL: Issues, https://github.com/suportly/spec-kit/issues
Author: spec-kit Contributors
License: MIT
License-File: LICENSE
Keywords: ai,development,litellm,llm,specification,workflow
Classifier: Development Status :: 3 - Alpha
Classifier: Intended Audience :: Developers
Classifier: License :: OSI Approved :: MIT License
Classifier: Programming Language :: Python :: 3
Classifier: Programming Language :: Python :: 3.11
Classifier: Programming Language :: Python :: 3.12
Classifier: Topic :: Software Development :: Libraries :: Python Modules
Requires-Python: >=3.11
Requires-Dist: httpx[socks]
Requires-Dist: instructor>=1.0.0
Requires-Dist: jinja2>=3.0.0
Requires-Dist: litellm>=1.0.0
Requires-Dist: platformdirs
Requires-Dist: pydantic-settings>=2.0.0
Requires-Dist: pydantic>=2.0.0
Requires-Dist: pyyaml>=6.0.0
Requires-Dist: readchar
Requires-Dist: rich>=13.0.0
Requires-Dist: truststore>=0.10.4
Requires-Dist: typer>=0.9.0
Provides-Extra: all
Requires-Dist: mcp>=1.0.0; extra == 'all'
Requires-Dist: mypy>=1.8.0; extra == 'all'
Requires-Dist: pytest-asyncio>=0.23.0; extra == 'all'
Requires-Dist: pytest-cov>=4.0.0; extra == 'all'
Requires-Dist: pytest>=8.0.0; extra == 'all'
Requires-Dist: ruff>=0.3.0; extra == 'all'
Provides-Extra: dev
Requires-Dist: mypy>=1.8.0; extra == 'dev'
Requires-Dist: pytest-asyncio>=0.23.0; extra == 'dev'
Requires-Dist: pytest-cov>=4.0.0; extra == 'dev'
Requires-Dist: pytest>=8.0.0; extra == 'dev'
Requires-Dist: ruff>=0.3.0; extra == 'dev'
Provides-Extra: mcp
Requires-Dist: mcp>=1.0.0; extra == 'mcp'
